ntlm_auth_md5/__init__.py
ntlm_auth_md5/compute_hash.py
ntlm_auth_md5/compute_keys.py
ntlm_auth_md5/compute_response.py
ntlm_auth_md5/constants.py
ntlm_auth_md5/des.py
ntlm_auth_md5/exceptions.py
ntlm_auth_md5/gss_channel_bindings.py
ntlm_auth_md5/messages.py
ntlm_auth_md5/ntlm.py
ntlm_auth_md5/rc4.py
ntlm_auth_md5/session_security.py
ntlm_auth_md5-0.0.1.dist-info/LICENSE
ntlm_auth_md5-0.0.1.dist-info/METADATA
ntlm_auth_md5-0.0.1.dist-info/WHEEL
ntlm_auth_md5-0.0.1.dist-info/top_level.txt
ntlm_auth_md5-0.0.1.dist-info/RECORD
